sampen/__init__.py
sampen/core.py
sampen_gpu-0.1.1.dist-info/licenses/LICENSE
sampen_gpu-0.1.1.dist-info/METADATA
sampen_gpu-0.1.1.dist-info/WHEEL
sampen_gpu-0.1.1.dist-info/top_level.txt
sampen_gpu-0.1.1.dist-info/RECORD
