Metadata-Version: 2.4
Name: sampen-gpu
Version: 0.1.1
Summary: GPU-accelerated Sample Entropy in Python
Author-email: Joseph Mifsud <jmifsud@posteo.net>
License: BSD-2 Clause
Requires-Python: >=3.8
License-File: LICENSE
Requires-Dist: numpy
Requires-Dist: numba
Dynamic: license-file
